{
  "classification_success_rate": 1.0,
  "combined_rank_change_history": [
    {
      "diagnostic_date": "2026-05-26",
      "max_rank_change": 2,
      "news_item_count": 4,
      "thin_news_warning": true
    },
    {
      "diagnostic_date": "2026-05-27",
      "max_rank_change": 2,
      "news_item_count": 5,
      "thin_news_warning": true
    },
    {
      "diagnostic_date": "2026-05-28",
      "max_rank_change": 2,
      "news_item_count": 7,
      "thin_news_warning": true
    },
    {
      "diagnostic_date": "2026-05-29",
      "max_rank_change": 2,
      "news_item_count": 27,
      "thin_news_warning": true
    },
    {
      "diagnostic_date": "2026-05-30",
      "max_rank_change": 2,
      "news_item_count": 36,
      "thin_news_warning": true
    },
    {
      "diagnostic_date": "2026-05-31",
      "max_rank_change": 2,
      "news_item_count": 39,
      "thin_news_warning": true
    }
  ],
  "daily_item_counts": {
    "2026-05-26": 7,
    "2026-05-27": 4,
    "2026-05-28": 17,
    "2026-05-29": 39,
    "2026-05-30": 12,
    "2026-05-31": 11
  },
  "date_end": "2026-05-31T12:18:24",
  "date_start": "2026-05-26T12:00:00",
  "disclaimer": "This is a diagnostic history report for news classification coverage and combined overlay behavior. It is not investment advice, market action guidance, execution guidance, or instructions for changing holdings.",
  "history_thresholds": {
    "early_history": "5 to 20 run dates",
    "insufficient_history": "fewer than 5 run dates or fewer than 100 classified items",
    "monitor_ready": "20+ run dates with reasonable source coverage",
    "validation_candidate": "60+ run dates with stable source coverage"
  },
  "latest_run": {
    "classified_items": 40,
    "created_at": "2026-05-31T12:52:26.305405",
    "date_max": "2026-05-31T12:18:24",
    "date_min": "2026-05-26T12:00:00",
    "duplicate_items": 0,
    "failed_items": 0,
    "new_unique_items": 102,
    "quality_status": "ok",
    "raw_item_count": 102,
    "run_date": "2026-05-31T00:00:00",
    "run_id": "20260531T125226Z-5668525a",
    "source_count": 14,
    "source_group_count": 10,
    "success_rate": 1.0,
    "warning_json": "[]"
  },
  "readiness_label": "insufficient_history",
  "source_count": 14,
  "source_group_count": 10,
  "top_recurring_macro_themes": [
    {
      "count": 6,
      "id": "growth_acceleration"
    },
    {
      "count": 3,
      "id": "geopolitical_risk"
    },
    {
      "count": 3,
      "id": "inflation_pressure"
    },
    {
      "count": 2,
      "id": "disinflation"
    },
    {
      "count": 2,
      "id": "energy_supply_shock"
    }
  ],
  "top_recurring_sector_headwinds": [
    {
      "count": 3,
      "id": "consumer_discretionary"
    },
    {
      "count": 2,
      "id": "financials"
    }
  ],
  "top_recurring_sector_tailwinds": [
    {
      "count": 6,
      "id": "health_care"
    },
    {
      "count": 6,
      "id": "information_technology"
    },
    {
      "count": 4,
      "id": "industrials"
    },
    {
      "count": 3,
      "id": "energy"
    },
    {
      "count": 3,
      "id": "real_estate"
    }
  ],
  "total_accumulated_news_items": 102,
  "total_classified_items": 40,
  "valid": true,
  "validation_note": "Do not treat the news overlay as empirically validated until enough balanced real-news history exists."
}